<?xml version="1.0" encoding="utf-8" standalone="yes"?>
<Gesture Name = "8">
	<Stroke>
		<Point X = "1230" Y = "-519" T = "0" Pressure = "0" />
		<Point X = "1249" Y = "-518" T = "0" Pressure = "0" />
		<Point X = "1263" Y = "-517" T = "0" Pressure = "0" />
		<Point X = "1280" Y = "-515" T = "0" Pressure = "0" />
		<Point X = "1296" Y = "-513" T = "0" Pressure = "0" />
		<Point X = "1309" Y = "-511" T = "0" Pressure = "0" />
		<Point X = "1316" Y = "-509" T = "0" Pressure = "0" />
		<Point X = "1321" Y = "-506" T = "0" Pressure = "0" />
		<Point X = "1322" Y = "-504" T = "0" Pressure = "0" />
		<Point X = "1323" Y = "-502" T = "0" Pressure = "0" />
		<Point X = "1323" Y = "-499" T = "0" Pressure = "0" />
		<Point X = "1323" Y = "-495" T = "0" Pressure = "0" />
		<Point X = "1321" Y = "-489" T = "0" Pressure = "0" />
		<Point X = "1316" Y = "-483" T = "0" Pressure = "0" />
		<Point X = "1311" Y = "-478" T = "0" Pressure = "0" />
		<Point X = "1304" Y = "-472" T = "0" Pressure = "0" />
		<Point X = "1297" Y = "-465" T = "0" Pressure = "0" />
		<Point X = "1294" Y = "-460" T = "0" Pressure = "0" />
		<Point X = "1291" Y = "-452" T = "0" Pressure = "0" />
		<Point X = "1289" Y = "-448" T = "0" Pressure = "0" />
		<Point X = "1284" Y = "-441" T = "0" Pressure = "0" />
		<Point X = "1277" Y = "-434" T = "0" Pressure = "0" />
		<Point X = "1269" Y = "-429" T = "0" Pressure = "0" />
		<Point X = "1263" Y = "-424" T = "0" Pressure = "0" />
		<Point X = "1257" Y = "-419" T = "0" Pressure = "0" />
		<Point X = "1256" Y = "-416" T = "0" Pressure = "0" />
		<Point X = "1254" Y = "-412" T = "0" Pressure = "0" />
		<Point X = "1254" Y = "-409" T = "0" Pressure = "0" />
		<Point X = "1254" Y = "-406" T = "0" Pressure = "0" />
		<Point X = "1254" Y = "-403" T = "0" Pressure = "0" />
		<Point X = "1254" Y = "-399" T = "0" Pressure = "0" />
		<Point X = "1258" Y = "-394" T = "0" Pressure = "0" />
		<Point X = "1263" Y = "-390" T = "0" Pressure = "0" />
		<Point X = "1269" Y = "-386" T = "0" Pressure = "0" />
		<Point X = "1277" Y = "-384" T = "0" Pressure = "0" />
		<Point X = "1282" Y = "-383" T = "0" Pressure = "0" />
		<Point X = "1289" Y = "-383" T = "0" Pressure = "0" />
		<Point X = "1297" Y = "-383" T = "0" Pressure = "0" />
		<Point X = "1306" Y = "-383" T = "0" Pressure = "0" />
		<Point X = "1313" Y = "-384" T = "0" Pressure = "0" />
		<Point X = "1321" Y = "-385" T = "0" Pressure = "0" />
		<Point X = "1324" Y = "-387" T = "0" Pressure = "0" />
		<Point X = "1324" Y = "-388" T = "0" Pressure = "0" />
		<Point X = "1325" Y = "-390" T = "0" Pressure = "0" />
		<Point X = "1325" Y = "-393" T = "0" Pressure = "0" />
		<Point X = "1325" Y = "-396" T = "0" Pressure = "0" />
		<Point X = "1324" Y = "-403" T = "0" Pressure = "0" />
		<Point X = "1320" Y = "-410" T = "0" Pressure = "0" />
		<Point X = "1316" Y = "-416" T = "0" Pressure = "0" />
		<Point X = "1309" Y = "-424" T = "0" Pressure = "0" />
		<Point X = "1299" Y = "-433" T = "0" Pressure = "0" />
		<Point X = "1293" Y = "-438" T = "0" Pressure = "0" />
		<Point X = "1279" Y = "-448" T = "0" Pressure = "0" />
		<Point X = "1268" Y = "-454" T = "0" Pressure = "0" />
		<Point X = "1255" Y = "-460" T = "0" Pressure = "0" />
		<Point X = "1244" Y = "-465" T = "0" Pressure = "0" />
		<Point X = "1233" Y = "-469" T = "0" Pressure = "0" />
		<Point X = "1227" Y = "-472" T = "0" Pressure = "0" />
		<Point X = "1222" Y = "-475" T = "0" Pressure = "0" />
		<Point X = "1219" Y = "-478" T = "0" Pressure = "0" />
		<Point X = "1217" Y = "-481" T = "0" Pressure = "0" />
		<Point X = "1215" Y = "-483" T = "0" Pressure = "0" />
		<Point X = "1215" Y = "-485" T = "0" Pressure = "0" />
		<Point X = "1214" Y = "-487" T = "0" Pressure = "0" />
		<Point X = "1213" Y = "-490" T = "0" Pressure = "0" />
		<Point X = "1212" Y = "-494" T = "0" Pressure = "0" />
		<Point X = "1212" Y = "-498" T = "0" Pressure = "0" />
		<Point X = "1211" Y = "-504" T = "0" Pressure = "0" />
		<Point X = "1210" Y = "-509" T = "0" Pressure = "0" />
		<Point X = "1210" Y = "-514" T = "0" Pressure = "0" />
		<Point X = "1210" Y = "-517" T = "0" Pressure = "0" />
		<Point X = "1214" Y = "-517" T = "0" Pressure = "0" />
		<Point X = "1217" Y = "-517" T = "0" Pressure = "0" />
		<Point X = "1224" Y = "-517" T = "0" Pressure = "0" />
		<Point X = "1229" Y = "-517" T = "0" Pressure = "0" />
		<Point X = "1232" Y = "-517" T = "0" Pressure = "0" />
		<Point X = "1234" Y = "-517" T = "0" Pressure = "0" />
		<Point X = "1235" Y = "-517" T = "0" Pressure = "0" />
		<Point X = "1236" Y = "-517" T = "0" Pressure = "0" />
		<Point X = "1238" Y = "-517" T = "0" Pressure = "0" />
		<Point X = "1242" Y = "-517" T = "0" Pressure = "0" />
		<Point X = "1247" Y = "-517" T = "0" Pressure = "0" />
		<Point X = "1251" Y = "-517" T = "0" Pressure = "0" />
		<Point X = "1255" Y = "-517" T = "0" Pressure = "0" />
	</Stroke>
</Gesture>
